timed_alert/__init__.py
timed_alert/main.py
timed_alert-0.1.dist-info/DESCRIPTION.rst
timed_alert-0.1.dist-info/METADATA
timed_alert-0.1.dist-info/RECORD
timed_alert-0.1.dist-info/WHEEL
timed_alert-0.1.dist-info/entry_points.txt
timed_alert-0.1.dist-info/metadata.json
timed_alert-0.1.dist-info/top_level.txt
